py3_web/__init__.py
py3_web/_html.py
py3_web/cookies.py
py3_web/headers.py
py3_web/http/__init__.py
py3_web/http/response.py
py3_web/url.py
py3_web-0.0.7.dist-info/METADATA
py3_web-0.0.7.dist-info/WHEEL
py3_web-0.0.7.dist-info/licenses/LICENSE
py3_web-0.0.7.dist-info/RECORD
