Metadata-Version: 2.4
Name: py3-web
Version: 0.0.7
Summary: python3 web
License-File: LICENSE
Author: mathewgeola
Author-email: mathewgeola@gmail.com
Requires-Python: >=3.12
Classifier: Programming Language :: Python :: 3
Classifier: Programming Language :: Python :: 3.12
Classifier: Programming Language :: Python :: 3.13
Classifier: Programming Language :: Python :: 3.14
Requires-Dist: bs4 (>=0.0.2,<0.0.3)
Requires-Dist: drissionpage (>=4.1.1.2,<5.0.0.0)
Requires-Dist: fake-useragent (>=2.2.0,<3.0.0)
Requires-Dist: furl (>=2.1.4,<3.0.0)
Requires-Dist: htmlmin (>=0.1.12,<0.2.0)
Requires-Dist: httpx (>=0.28.1,<0.29.0)
Requires-Dist: py3-execute (>=0.0.5,<0.0.6)
Requires-Dist: py3-logger (>=0.0.7,<0.0.8)
Requires-Dist: requests (>=2.32.5,<3.0.0)
Requires-Dist: scrapy (>=2.14.0,<3.0.0)
